concrete_strength_prediction/__init__.py
concrete_strength_prediction/py.typed
concrete_strength_prediction/config/__init__.py
concrete_strength_prediction/config/core.py
concrete_strength_prediction/utils/__init__.py
concrete_strength_prediction/utils/data_manager.py
tests/__init__.py
tests/conftest.py
concrete_strength_prediction-0.1.4.dist-info/LICENSE
concrete_strength_prediction-0.1.4.dist-info/METADATA
concrete_strength_prediction-0.1.4.dist-info/WHEEL
concrete_strength_prediction-0.1.4.dist-info/top_level.txt
concrete_strength_prediction-0.1.4.dist-info/RECORD
